brig/__init__.py
brig/PoolExecutor/__init__.py
brig/PoolExecutor/base.py
brig/PoolExecutor/executor.py
brig-0.0.1.dist-info/LICENSE
brig-0.0.1.dist-info/METADATA
brig-0.0.1.dist-info/WHEEL
brig-0.0.1.dist-info/RECORD
