Metadata-Version: 2.1
Name: brig
Version: 0.0.1
Summary: It is a repository for all modified functions and classes.
License: AGPL-3.0-or-later
Author: Code63Reaper
Author-email: akilangms542@gmail.com
Maintainer: Code63Reaper
Maintainer-email: akilangms542@gmail.com
Requires-Python: >=3.10,<4.0
Classifier: Development Status :: 2 - Pre-Alpha
Classifier: Intended Audience :: Developers
Classifier: License :: OSI Approved :: GNU Affero General Public License v3 or later (AGPLv3+)
Classifier: Programming Language :: Python :: 3
Classifier: Programming Language :: Python :: 3.10
Classifier: Programming Language :: Python :: 3.11
Classifier: Programming Language :: Python :: 3.12
Classifier: Programming Language :: Python :: 3 :: Only
Classifier: Topic :: Utilities
Requires-Dist: tqdm (>=4.66.5,<5.0.0)
